[
  {
    "Simulation":1,
    "Winner":"Team 4",
    "Roster":[
      "Dalvin Cook \/ 7.95",
      "Aaron Jones \/ 20.90",
      "David Johnson \/ 32.70",
      "Robert Woods \/ 53.60",
      "Darren Waller \/ 61.30",
      "Dak Prescott \/ 75.90",
      "Stefon Diggs \/ 59.00",
      "Zack Moss \/ 94.30",
      "Tarik Cohen \/ 93.80",
      "John Brown \/ 118.00",
      "Justice Hill \/ 119.00",
      "Dallas Goedert \/ 136.00",
      "Ryan Succop \/ 139.00",
      "Chiefs \/ 147.00",
      "Philip Rivers \/ 139.00"
    ],
    "Points Reg Season":1579.5,
    "Points Full Season":1863.32
  },
  {
    "Simulation":2,
    "Winner":"Team 3",
    "Roster":[
      "Alvin Kamara \/ 4.22",
      "Miles Sanders \/ 27.50",
      "David Johnson \/ 32.70",
      "D.J. Moore \/ 47.00",
      "Chris Godwin \/ 30.00",
      "Kareem Hunt \/ 75.80",
      "Evan Engram \/ 74.90",
      "Delanie Walker \/ 98.70",
      "Christian Kirk \/ 105.00",
      "Sterling Shepard \/ 113.00",
      "Matt Breida \/ 94.00",
      "Ben Roethlisberger \/ 122.00",
      "Harrison Butker \/ 125.00",
      "Broncos \/ 162.00",
      "Mitchell Trubisky \/ 138.00"
    ],
    "Points Reg Season":1359.34,
    "Points Full Season":1625.14
  },
  {
    "Simulation":3,
    "Winner":"Team 8",
    "Roster":[
      "Nick Chubb \/ 13.00",
      "Todd Gurley \/ 24.50",
      "Lamar Jackson \/ 42.00",
      "Adam Thielen \/ 31.60",
      "D'Andre Swift \/ 68.80",
      "Tyler Higbee \/ 77.30",
      "Sony Michel \/ 80.90",
      "Matt Breida \/ 94.00",
      "Antonio Gibson \/ 82.10",
      "CeeDee Lamb \/ 105.00",
      "Deebo Samuel \/ 120.00",
      "Austin Hooper \/ 132.00",
      "Mike Badgley \/ 149.00",
      "Saints \/ 139.00",
      "Jimmy Garoppolo \/ 148.00"
    ],
    "Points Reg Season":1327.8,
    "Points Full Season":1558.04
  },
  {
    "Simulation":4,
    "Winner":"Team 11",
    "Roster":[
      "Tyreek Hill \/ 14.20",
      "Patrick Mahomes \/ 16.40",
      "Zach Ertz \/ 43.10",
      "Melvin Gordon \/ 38.30",
      "Mark Andrews \/ 71.60",
      "Cooper Kupp \/ 43.20",
      "Michael Gallup \/ 89.80",
      "Marlon Mack \/ 79.40",
      "Josh Allen \/ 105.00",
      "Mike Williams \/ 116.00",
      "Darrell Henderson \/ 124.00",
      "Bears \/ 116.00",
      "Tua Tagovailoa \/ 124.00",
      "Dan Bailey \/ 166.00",
      "Jacoby Brissett \/ 164.00"
    ],
    "Points Reg Season":1384.68,
    "Points Full Season":1585.94
  },
  {
    "Simulation":5,
    "Winner":"Team 4",
    "Roster":[
      "Ezekiel Elliott \/ 3.44",
      "Tyreek Hill \/ 14.20",
      "Kenyan Drake \/ 36.80",
      "Deshaun Watson \/ 54.00",
      "D'Andre Swift \/ 68.80",
      "A.J. Green \/ 77.60",
      "Mark Andrews \/ 71.60",
      "Michael Gallup \/ 89.80",
      "Ravens \/ 108.00",
      "Robby Anderson \/ 114.00",
      "Darius Slayton \/ 120.00",
      "Hunter Renfrow \/ 126.00",
      "T.J. Hockenson \/ 138.00",
      "Kaimi Fairbairn \/ 168.00",
      "Philip Rivers \/ 139.00"
    ],
    "Points Reg Season":1369.22,
    "Points Full Season":1545.7
  },
  {
    "Simulation":6,
    "Winner":"Team 11",
    "Roster":[
      "Joe Mixon \/ 13.10",
      "Derrick Henry \/ 16.10",
      "Cooper Kupp \/ 43.20",
      "Kenny Golladay \/ 36.40",
      "Darren Waller \/ 61.30",
      "Evan Engram \/ 74.90",
      "Aaron Rodgers \/ 88.10",
      "Matt Breida \/ 94.00",
      "Royce Freeman \/ 108.00",
      "Devonta Freeman \/ 117.00",
      "Jerry Jeudy \/ 120.00",
      "Diontae Johnson \/ 108.00",
      "Younghoe Koo \/ 160.00",
      "Bills \/ 135.00",
      "Derek Carr \/ 156.00"
    ],
    "Points Reg Season":1423.04,
    "Points Full Season":1642.5
  },
  {
    "Simulation":7,
    "Winner":"Team 4",
    "Roster":[
      "Dalvin Cook \/ 7.95",
      "George Kittle \/ 24.50",
      "David Johnson \/ 32.70",
      "Deshaun Watson \/ 54.00",
      "Stefon Diggs \/ 59.00",
      "T.Y. Hilton \/ 62.00",
      "Darwin Thompson \/ 79.50",
      "Hayden Hurst \/ 100.00",
      "Michael Gallup \/ 89.80",
      "Justice Hill \/ 119.00",
      "Jerry Jeudy \/ 120.00",
      "James Robinson \/ 127.00",
      "Greg Zuerlein \/ 136.00",
      "Chiefs \/ 147.00",
      "Mitchell Trubisky \/ 138.00"
    ],
    "Points Reg Season":1482.04,
    "Points Full Season":1774.52
  },
  {
    "Simulation":8,
    "Winner":"Team 6",
    "Roster":[
      "Clyde Edwards-Helaire \/ 9.22",
      "Chris Carson \/ 26.40",
      "Jonathan Taylor \/ 38.40",
      "Calvin Ridley \/ 53.10",
      "Stefon Diggs \/ 59.00",
      "A.J. Green \/ 77.60",
      "Evan Engram \/ 74.90",
      "Jordan Howard \/ 87.90",
      "Diontae Johnson \/ 108.00",
      "Noah Fant \/ 119.00",
      "Ben Roethlisberger \/ 122.00",
      "Royce Freeman \/ 108.00",
      "Mike Badgley \/ 149.00",
      "Rams \/ 140.00",
      "Joe Burrow \/ 143.00"
    ],
    "Points Reg Season":1448.66,
    "Points Full Season":1711.4
  },
  {
    "Simulation":9,
    "Winner":"Team 3",
    "Roster":[
      "Alvin Kamara \/ 4.22",
      "Miles Sanders \/ 27.50",
      "David Johnson \/ 32.70",
      "Terry McLaurin \/ 55.00",
      "Allen Robinson \/ 47.10",
      "Drew Brees \/ 80.10",
      "Darwin Thompson \/ 79.50",
      "Delanie Walker \/ 98.70",
      "Diontae Johnson \/ 108.00",
      "Emmanuel Sanders \/ 105.00",
      "Justin Jefferson \/ 122.00",
      "Blake Jarwin \/ 145.00",
      "Greg Zuerlein \/ 136.00",
      "Chiefs \/ 147.00",
      "Mitchell Trubisky \/ 138.00"
    ],
    "Points Reg Season":1312.38,
    "Points Full Season":1581.74
  },
  {
    "Simulation":10,
    "Winner":"Team 7",
    "Roster":[
      "Davante Adams \/ 11.30",
      "Derrick Henry \/ 16.10",
      "Kenny Golladay \/ 36.40",
      "Raheem Mostert \/ 45.70",
      "David Montgomery \/ 54.80",
      "Courtland Sutton \/ 77.70",
      "Marquise Brown \/ 74.00",
      "Carson Wentz \/ 89.30",
      "Hayden Hurst \/ 100.00",
      "Tom Brady \/ 94.20",
      "Justin Tucker \/ 123.00",
      "Darrell Henderson \/ 124.00",
      "Blake Jarwin \/ 145.00",
      "Rams \/ 140.00",
      "Kirk Cousins \/ 147.00"
    ],
    "Points Reg Season":1374.3,
    "Points Full Season":1635.42
  },
  {
    "Simulation":11,
    "Winner":"Team 8",
    "Roster":[
      "Nick Chubb \/ 13.00",
      "Derrick Henry \/ 16.10",
      "Adam Thielen \/ 31.60",
      "Calvin Ridley \/ 53.10",
      "David Montgomery \/ 54.80",
      "Mark Andrews \/ 71.60",
      "Brandin Cooks \/ 82.50",
      "Delanie Walker \/ 98.70",
      "Josh Allen \/ 105.00",
      "Royce Freeman \/ 108.00",
      "Darrell Henderson \/ 124.00",
      "Ryquell Armstead \/ 126.00",
      "Ryan Succop \/ 139.00",
      "Patriots \/ 139.00",
      "Kirk Cousins \/ 147.00"
    ],
    "Points Reg Season":1619.7,
    "Points Full Season":1926.56
  },
  {
    "Simulation":12,
    "Winner":"Team 8",
    "Roster":[
      "Davante Adams \/ 11.30",
      "Aaron Jones \/ 20.90",
      "Amari Cooper \/ 39.60",
      "Leonard Fournette \/ 44.00",
      "Kyler Murray \/ 71.20",
      "Tyler Lockett \/ 52.60",
      "Marquise Brown \/ 74.00",
      "James White \/ 83.20",
      "Ravens \/ 108.00",
      "Marquez Valdes-Scantling \/ 103.00",
      "Henry Ruggs \/ 122.00",
      "O.J. Howard \/ 125.00",
      "T.J. Hockenson \/ 138.00",
      "Matt Prater \/ 165.00",
      "Ryan Tannehill \/ 147.00"
    ],
    "Points Reg Season":1535.96,
    "Points Full Season":1763.28
  },
  {
    "Simulation":13,
    "Winner":"Team 4",
    "Roster":[
      "Dalvin Cook \/ 7.95",
      "James Conner \/ 20.50",
      "Adam Thielen \/ 31.60",
      "Cooper Kupp \/ 43.20",
      "D'Andre Swift \/ 68.80",
      "Drew Brees \/ 80.10",
      "Robert Woods \/ 53.60",
      "Phillip Lindsay \/ 80.50",
      "Marvin Jones \/ 99.60",
      "Bears \/ 116.00",
      "Darius Slayton \/ 120.00",
      "T.J. Hockenson \/ 138.00",
      "Chris Herndon \/ 146.00",
      "Dan Bailey \/ 166.00",
      "Philip Rivers \/ 139.00"
    ],
    "Points Reg Season":1445.32,
    "Points Full Season":1632.62
  },
  {
    "Simulation":14,
    "Winner":"Team 7",
    "Roster":[
      "Davante Adams \/ 11.30",
      "Todd Gurley \/ 24.50",
      "LeVeon Bell \/ 29.30",
      "Robert Woods \/ 53.60",
      "Darren Waller \/ 61.30",
      "Dak Prescott \/ 75.90",
      "Drew Brees \/ 80.10",
      "Antonio Gibson \/ 82.10",
      "Royce Freeman \/ 108.00",
      "Tony Pollard \/ 114.00",
      "Marquez Valdes-Scantling \/ 103.00",
      "Mike Gesicki \/ 132.00",
      "Mike Badgley \/ 149.00",
      "Saints \/ 139.00",
      "Kirk Cousins \/ 147.00"
    ],
    "Points Reg Season":1517.68,
    "Points Full Season":1748.68
  },
  {
    "Simulation":15,
    "Winner":"Team 4",
    "Roster":[
      "Ezekiel Elliott \/ 3.44",
      "Miles Sanders \/ 27.50",
      "Chris Carson \/ 26.40",
      "Raheem Mostert \/ 45.70",
      "Terry McLaurin \/ 55.00",
      "Drew Brees \/ 80.10",
      "James White \/ 83.20",
      "Brandin Cooks \/ 82.50",
      "Emmanuel Sanders \/ 105.00",
      "Marquez Valdes-Scantling \/ 103.00",
      "Kyle Rudolph \/ 120.00",
      "Dallas Goedert \/ 136.00",
      "Ryan Succop \/ 139.00",
      "Chiefs \/ 147.00",
      "Mitchell Trubisky \/ 138.00"
    ],
    "Points Reg Season":1199.28,
    "Points Full Season":1401.84
  },
  {
    "Simulation":16,
    "Winner":"Team 9",
    "Roster":[
      "Nick Chubb \/ 13.00",
      "Aaron Jones \/ 20.90",
      "Lamar Jackson \/ 42.00",
      "Jonathan Taylor \/ 38.40",
      "Calvin Ridley \/ 53.10",
      "Kareem Hunt \/ 75.80",
      "Jordan Howard \/ 87.90",
      "Carson Wentz \/ 89.30",
      "Brandin Cooks \/ 82.50",
      "Delanie Walker \/ 98.70",
      "CeeDee Lamb \/ 105.00",
      "Trey Burton \/ 130.00",
      "Zane Gonzalez \/ 150.00",
      "Vikings \/ 137.00",
      "Drew Lock \/ 155.00"
    ],
    "Points Reg Season":1395.08,
    "Points Full Season":1644.32
  },
  {
    "Simulation":17,
    "Winner":"Team 5",
    "Roster":[
      "Ezekiel Elliott \/ 3.44",
      "Travis Kelce \/ 18.30",
      "JuJu Smith-Schuster \/ 31.80",
      "Robert Woods \/ 53.60",
      "David Montgomery \/ 54.80",
      "Darwin Thompson \/ 79.50",
      "Will Fuller \/ 83.20",
      "Zack Moss \/ 94.30",
      "Duke Johnson \/ 107.00",
      "Noah Fant \/ 119.00",
      "Dante Pettis \/ 120.00",
      "Ben Roethlisberger \/ 122.00",
      "Ryan Succop \/ 139.00",
      "Rams \/ 140.00",
      "Joe Burrow \/ 143.00"
    ],
    "Points Reg Season":1493.92,
    "Points Full Season":1737.96
  },
  {
    "Simulation":18,
    "Winner":"Team 10",
    "Roster":[
      "Joe Mixon \/ 13.10",
      "Josh Jacobs \/ 19.70",
      "Zach Ertz \/ 43.10",
      "Amari Cooper \/ 39.60",
      "Stefon Diggs \/ 59.00",
      "Hunter Henry \/ 76.40",
      "Carson Wentz \/ 89.30",
      "Matt Breida \/ 94.00",
      "Steelers \/ 105.00",
      "Jared Goff \/ 114.00",
      "Zack Moss \/ 94.30",
      "Antonio Brown \/ 128.00",
      "Ravens \/ 108.00",
      "Dan Bailey \/ 166.00",
      "Derek Carr \/ 156.00"
    ],
    "Points Reg Season":1246.72,
    "Points Full Season":1456.64
  },
  {
    "Simulation":19,
    "Winner":"Team 12",
    "Roster":[
      "Tyreek Hill \/ 14.20",
      "Patrick Mahomes \/ 16.40",
      "Zach Ertz \/ 43.10",
      "Leonard Fournette \/ 44.00",
      "Calvin Ridley \/ 53.10",
      "Hunter Henry \/ 76.40",
      "Devin Singletary \/ 66.40",
      "Brandin Cooks \/ 82.50",
      "Sterling Shepard \/ 113.00",
      "Tom Brady \/ 94.20",
      "Peyton Barber \/ 116.00",
      "Hunter Renfrow \/ 126.00",
      "Kaimi Fairbairn \/ 168.00",
      "Steelers \/ 105.00",
      "Derek Carr \/ 156.00"
    ],
    "Points Reg Season":1352.36,
    "Points Full Season":1593.14
  },
  {
    "Simulation":20,
    "Winner":"Team 1",
    "Roster":[
      "Christian McCaffrey \/ 1.92",
      "Todd Gurley \/ 24.50",
      "Mike Evans \/ 27.90",
      "David Montgomery \/ 54.80",
      "Stefon Diggs \/ 59.00",
      "J.K. Dobbins \/ 81.40",
      "Jarvis Landry \/ 82.40",
      "Josh Allen \/ 105.00",
      "CeeDee Lamb \/ 105.00",
      "Deebo Samuel \/ 120.00",
      "Eric Ebron \/ 119.00",
      "Jonnu Smith \/ 144.00",
      "Justin Tucker \/ 123.00",
      "Cowboys \/ 162.00",
      "Ben Roethlisberger \/ 122.00"
    ],
    "Points Reg Season":1492.62,
    "Points Full Season":1811.78
  },
  {
    "Simulation":21,
    "Winner":"Team 7",
    "Roster":[
      "Davante Adams \/ 11.30",
      "George Kittle \/ 24.50",
      "Chris Godwin \/ 30.00",
      "Robert Woods \/ 53.60",
      "Darren Waller \/ 61.30",
      "DK Metcalf \/ 76.30",
      "Drew Brees \/ 80.10",
      "Rashaad Penny \/ 91.90",
      "Hayden Hurst \/ 100.00",
      "Baker Mayfield \/ 111.00",
      "Tony Pollard \/ 114.00",
      "Devonta Freeman \/ 117.00",
      "Stephen Gostkowski \/ 144.00",
      "Saints \/ 139.00",
      "Joe Burrow \/ 143.00"
    ],
    "Points Reg Season":1339.04,
    "Points Full Season":1554.4
  },
  {
    "Simulation":22,
    "Winner":"Team 2",
    "Roster":[
      "Ezekiel Elliott \/ 3.44",
      "Mike Evans \/ 27.90",
      "David Johnson \/ 32.70",
      "Terry McLaurin \/ 55.00",
      "Darren Waller \/ 61.30",
      "Rob Gronkowski \/ 80.50",
      "A.J. Green \/ 77.60",
      "Kyler Murray \/ 71.20",
      "Zack Moss \/ 94.30",
      "Jordan Howard \/ 87.90",
      "Ben Roethlisberger \/ 122.00",
      "Tarik Cohen \/ 93.80",
      "Greg Zuerlein \/ 136.00",
      "Broncos \/ 162.00",
      "Daniel Jones \/ 129.00"
    ],
    "Points Reg Season":1348.88,
    "Points Full Season":1630.7
  },
  {
    "Simulation":23,
    "Winner":"Team 3",
    "Roster":[
      "Alvin Kamara \/ 4.22",
      "Mike Evans \/ 27.90",
      "JuJu Smith-Schuster \/ 31.80",
      "Calvin Ridley \/ 53.10",
      "DeVante Parker \/ 66.30",
      "Kyler Murray \/ 71.20",
      "Darwin Thompson \/ 79.50",
      "Zack Moss \/ 94.30",
      "Latavius Murray \/ 94.90",
      "Baker Mayfield \/ 111.00",
      "Noah Fant \/ 119.00",
      "Dallas Goedert \/ 136.00",
      "Greg Zuerlein \/ 136.00",
      "Broncos \/ 162.00",
      "Matthew Stafford \/ 126.00"
    ],
    "Points Reg Season":1519.78,
    "Points Full Season":1800.1
  },
  {
    "Simulation":24,
    "Winner":"Team 5",
    "Roster":[
      "Alvin Kamara \/ 4.22",
      "Odell Beckham \/ 27.20",
      "Austin Ekeler \/ 30.00",
      "Josh Jacobs \/ 19.70",
      "Stefon Diggs \/ 59.00",
      "Matt Ryan \/ 74.50",
      "Brandin Cooks \/ 82.50",
      "Marvin Jones \/ 99.60",
      "Tevin Coleman \/ 93.50",
      "Bears \/ 116.00",
      "Duke Johnson \/ 107.00",
      "Mike Gesicki \/ 132.00",
      "Chris Herndon \/ 146.00",
      "Matt Prater \/ 165.00",
      "Joe Burrow \/ 143.00"
    ],
    "Points Reg Season":1452.12,
    "Points Full Season":1734.16
  },
  {
    "Simulation":25,
    "Winner":"Team 4",
    "Roster":[
      "Dalvin Cook \/ 7.95",
      "Odell Beckham \/ 27.20",
      "David Johnson \/ 32.70",
      "Calvin Ridley \/ 53.10",
      "D.J. Chark \/ 56.40",
      "D'Andre Swift \/ 68.80",
      "DK Metcalf \/ 76.30",
      "Jared Cook \/ 91.10",
      "Josh Allen \/ 105.00",
      "Hayden Hurst \/ 100.00",
      "Geronimo Allison \/ 111.00",
      "Devonta Freeman \/ 117.00",
      "Wil Lutz \/ 137.00",
      "Chiefs \/ 147.00",
      "Mitchell Trubisky \/ 138.00"
    ],
    "Points Reg Season":1462.76,
    "Points Full Season":1754.12
  },
  {
    "Simulation":26,
    "Winner":"Team 2",
    "Roster":[
      "Ezekiel Elliott \/ 3.44",
      "Miles Sanders \/ 27.50",
      "David Johnson \/ 32.70",
      "David Montgomery \/ 54.80",
      "Russell Wilson \/ 64.80",
      "DK Metcalf \/ 76.30",
      "J.K. Dobbins \/ 81.40",
      "Phillip Lindsay \/ 80.50",
      "Brandin Cooks \/ 82.50",
      "Eric Ebron \/ 119.00",
      "Michael Gallup \/ 89.80",
      "T.J. Hockenson \/ 138.00",
      "Greg Zuerlein \/ 136.00",
      "Chargers \/ 153.00",
      "Tua Tagovailoa \/ 124.00"
    ],
    "Points Reg Season":1419.8,
    "Points Full Season":1642.34
  },
  {
    "Simulation":27,
    "Winner":"Team 3",
    "Roster":[
      "Alvin Kamara \/ 4.22",
      "Miles Sanders \/ 27.50",
      "Kenny Golladay \/ 36.40",
      "David Montgomery \/ 54.80",
      "Stefon Diggs \/ 59.00",
      "Evan Engram \/ 74.90",
      "A.J. Green \/ 77.60",
      "Deshaun Watson \/ 54.00",
      "Aaron Rodgers \/ 88.10",
      "Sterling Shepard \/ 113.00",
      "Henry Ruggs \/ 122.00",
      "Blake Jarwin \/ 145.00",
      "Greg Zuerlein \/ 136.00",
      "Chiefs \/ 147.00",
      "Mitchell Trubisky \/ 138.00"
    ],
    "Points Reg Season":1453.92,
    "Points Full Season":1772.6
  },
  {
    "Simulation":28,
    "Winner":"Team 7",
    "Roster":[
      "Dalvin Cook \/ 7.95",
      "Todd Gurley \/ 24.50",
      "Amari Cooper \/ 39.60",
      "Lamar Jackson \/ 42.00",
      "Darren Waller \/ 61.30",
      "Cam Akers \/ 55.60",
      "Brandin Cooks \/ 82.50",
      "Matt Breida \/ 94.00",
      "Josh Allen \/ 105.00",
      "Peyton Barber \/ 116.00",
      "CeeDee Lamb \/ 105.00",
      "Austin Hooper \/ 132.00",
      "Mike Badgley \/ 149.00",
      "Vikings \/ 137.00",
      "Jimmy Garoppolo \/ 148.00"
    ],
    "Points Reg Season":1523.02,
    "Points Full Season":1778.66
  },
  {
    "Simulation":29,
    "Winner":"Team 12",
    "Roster":[
      "Joe Mixon \/ 13.10",
      "Travis Kelce \/ 18.30",
      "Cooper Kupp \/ 43.20",
      "Leonard Fournette \/ 44.00",
      "Kareem Hunt \/ 75.80",
      "Tyler Boyd \/ 74.60",
      "Jared Cook \/ 91.10",
      "Tevin Coleman \/ 93.50",
      "Rashaad Penny \/ 91.90",
      "Steelers \/ 105.00",
      "Darrell Henderson \/ 124.00",
      "Josh Allen \/ 105.00",
      "Geronimo Allison \/ 111.00",
      "Matt Prater \/ 165.00",
      "Teddy Bridgewater \/ 161.00"
    ],
    "Points Reg Season":1402.44,
    "Points Full Season":1614.7
  },
  {
    "Simulation":30,
    "Winner":"Team 10",
    "Roster":[
      "Joe Mixon \/ 13.10",
      "Patrick Mahomes \/ 16.40",
      "Amari Cooper \/ 39.60",
      "A.J. Brown \/ 42.30",
      "Stefon Diggs \/ 59.00",
      "Matt Ryan \/ 74.50",
      "Aaron Rodgers \/ 88.10",
      "David Njoku \/ 83.80",
      "CeeDee Lamb \/ 105.00",
      "Sony Michel \/ 80.90",
      "Tony Pollard \/ 114.00",
      "Trey Burton \/ 130.00",
      "Zane Gonzalez \/ 150.00",
      "Vikings \/ 137.00",
      "Drew Lock \/ 155.00"
    ],
    "Points Reg Season":1339.02,
    "Points Full Season":1542.76
  },
  {
    "Simulation":31,
    "Winner":"Team 4",
    "Roster":[
      "Alvin Kamara \/ 4.22",
      "Chris Carson \/ 26.40",
      "Kenyan Drake \/ 36.80",
      "Terry McLaurin \/ 55.00",
      "D.J. Moore \/ 47.00",
      "Allen Robinson \/ 47.10",
      "Dak Prescott \/ 75.90",
      "Josh Allen \/ 105.00",
      "Kerryon Johnson \/ 87.40",
      "Royce Freeman \/ 108.00",
      "Noah Fant \/ 119.00",
      "Jonnu Smith \/ 144.00",
      "Wil Lutz \/ 137.00",
      "Chargers \/ 153.00",
      "Ryan Tannehill \/ 147.00"
    ],
    "Points Reg Season":1531.7,
    "Points Full Season":1816.56
  },
  {
    "Simulation":32,
    "Winner":"Team 4",
    "Roster":[
      "Dalvin Cook \/ 7.95",
      "Aaron Jones \/ 20.90",
      "Adam Thielen \/ 31.60",
      "Robert Woods \/ 53.60",
      "Darren Waller \/ 61.30",
      "Tyler Boyd \/ 74.60",
      "Rob Gronkowski \/ 80.50",
      "Tom Brady \/ 94.20",
      "Hayden Hurst \/ 100.00",
      "CeeDee Lamb \/ 105.00",
      "Justice Hill \/ 119.00",
      "Tony Pollard \/ 114.00",
      "Ryan Succop \/ 139.00",
      "Chiefs \/ 147.00",
      "Philip Rivers \/ 139.00"
    ],
    "Points Reg Season":1625.68,
    "Points Full Season":1916.4
  },
  {
    "Simulation":33,
    "Winner":"Team 10",
    "Roster":[
      "Joe Mixon \/ 13.10",
      "Derrick Henry \/ 16.10",
      "Jonathan Taylor \/ 38.40",
      "Allen Robinson \/ 47.10",
      "Mark Andrews \/ 71.60",
      "T.Y. Hilton \/ 62.00",
      "Jordan Howard \/ 87.90",
      "Tevin Coleman \/ 93.50",
      "Ravens \/ 108.00",
      "Emmanuel Sanders \/ 105.00",
      "Justin Jefferson \/ 122.00",
      "Tua Tagovailoa \/ 124.00",
      "Jonnu Smith \/ 144.00",
      "Younghoe Koo \/ 160.00",
      "Derek Carr \/ 156.00"
    ],
    "Points Reg Season":1373.34,
    "Points Full Season":1592.4
  },
  {
    "Simulation":34,
    "Winner":"Team 8",
    "Roster":[
      "Nick Chubb \/ 13.00",
      "Travis Kelce \/ 18.30",
      "Lamar Jackson \/ 42.00",
      "Calvin Ridley \/ 53.10",
      "D'Andre Swift \/ 68.80",
      "Dak Prescott \/ 75.90",
      "Aaron Rodgers \/ 88.10",
      "Jarvis Landry \/ 82.40",
      "Marlon Mack \/ 79.40",
      "Royce Freeman \/ 108.00",
      "Darius Slayton \/ 120.00",
      "Eric Ebron \/ 119.00",
      "Mike Badgley \/ 149.00",
      "Saints \/ 139.00",
      "Gardner Minshew \/ 155.00"
    ],
    "Points Reg Season":1343.58,
    "Points Full Season":1592.12
  },
  {
    "Simulation":35,
    "Winner":"Team 5",
    "Roster":[
      "Michael Thomas \/ 8.48",
      "Travis Kelce \/ 18.30",
      "Miles Sanders \/ 27.50",
      "Robert Woods \/ 53.60",
      "D.J. Chark \/ 56.40",
      "Hunter Henry \/ 76.40",
      "Brandin Cooks \/ 82.50",
      "Carson Wentz \/ 89.30",
      "Kyler Murray \/ 71.20",
      "Ravens \/ 108.00",
      "Justin Jefferson \/ 122.00",
      "Ronald Jones \/ 110.00",
      "Tony Pollard \/ 114.00",
      "Kaimi Fairbairn \/ 168.00",
      "Joe Burrow \/ 143.00"
    ],
    "Points Reg Season":1447.72,
    "Points Full Season":1689.34
  },
  {
    "Simulation":36,
    "Winner":"Team 1",
    "Roster":[
      "Saquon Barkley \/ 2.13",
      "Austin Ekeler \/ 30.00",
      "Travis Kelce \/ 18.30",
      "Melvin Gordon \/ 38.30",
      "Kenyan Drake \/ 36.80",
      "Sony Michel \/ 80.90",
      "Jarvis Landry \/ 82.40",
      "CeeDee Lamb \/ 105.00",
      "Tevin Coleman \/ 93.50",
      "Josh Allen \/ 105.00",
      "Sterling Shepard \/ 113.00",
      "Dallas Goedert \/ 136.00",
      "Justin Tucker \/ 123.00",
      "Broncos \/ 162.00",
      "Tua Tagovailoa \/ 124.00"
    ],
    "Points Reg Season":1325.78,
    "Points Full Season":1585.04
  },
  {
    "Simulation":37,
    "Winner":"Team 7",
    "Roster":[
      "Davante Adams \/ 11.30",
      "George Kittle \/ 24.50",
      "Jonathan Taylor \/ 38.40",
      "Leonard Fournette \/ 44.00",
      "Marquise Brown \/ 74.00",
      "Julian Edelman \/ 74.10",
      "J.K. Dobbins \/ 81.40",
      "Tevin Coleman \/ 93.50",
      "Geronimo Allison \/ 111.00",
      "Bears \/ 116.00",
      "Eric Ebron \/ 119.00",
      "Ryquell Armstead \/ 126.00",
      "Matthew Stafford \/ 126.00",
      "Kaimi Fairbairn \/ 168.00",
      "Jimmy Garoppolo \/ 148.00"
    ],
    "Points Reg Season":1220.48,
    "Points Full Season":1439.14
  },
  {
    "Simulation":38,
    "Winner":"Team 11",
    "Roster":[
      "DeAndre Hopkins \/ 13.40",
      "Derrick Henry \/ 16.10",
      "Amari Cooper \/ 39.60",
      "Leonard Fournette \/ 44.00",
      "Allen Robinson \/ 47.10",
      "Evan Engram \/ 74.90",
      "Jarvis Landry \/ 82.40",
      "Aaron Rodgers \/ 88.10",
      "Royce Freeman \/ 108.00",
      "Ravens \/ 108.00",
      "Matthew Stafford \/ 126.00",
      "Jerry Jeudy \/ 120.00",
      "Blake Jarwin \/ 145.00",
      "Matt Prater \/ 165.00",
      "Derek Carr \/ 156.00"
    ],
    "Points Reg Season":1457.58,
    "Points Full Season":1689.54
  },
  {
    "Simulation":39,
    "Winner":"Team 9",
    "Roster":[
      "Joe Mixon \/ 13.10",
      "Tyreek Hill \/ 14.20",
      "Kenyan Drake \/ 36.80",
      "Leonard Fournette \/ 44.00",
      "Matt Ryan \/ 74.50",
      "Kareem Hunt \/ 75.80",
      "Aaron Rodgers \/ 88.10",
      "Jared Cook \/ 91.10",
      "Sterling Shepard \/ 113.00",
      "Tony Pollard \/ 114.00",
      "Will Fuller \/ 83.20",
      "Trey Burton \/ 130.00",
      "Stephen Gostkowski \/ 144.00",
      "Saints \/ 139.00",
      "Drew Lock \/ 155.00"
    ],
    "Points Reg Season":1500.84,
    "Points Full Season":1708.7
  },
  {
    "Simulation":40,
    "Winner":"Team 6",
    "Roster":[
      "Michael Thomas \/ 8.48",
      "Travis Kelce \/ 18.30",
      "Jonathan Taylor \/ 38.40",
      "Leonard Fournette \/ 44.00",
      "Calvin Ridley \/ 53.10",
      "Kareem Hunt \/ 75.80",
      "Brandin Cooks \/ 82.50",
      "Jared Cook \/ 91.10",
      "Hayden Hurst \/ 100.00",
      "Jared Goff \/ 114.00",
      "Dante Pettis \/ 120.00",
      "Matthew Stafford \/ 126.00",
      "Ryan Succop \/ 139.00",
      "Patriots \/ 139.00",
      "Kirk Cousins \/ 147.00"
    ],
    "Points Reg Season":1359.06,
    "Points Full Season":1614.28
  },
  {
    "Simulation":41,
    "Winner":"Team 7",
    "Roster":[
      "Davante Adams \/ 11.30",
      "Aaron Jones \/ 20.90",
      "Adam Thielen \/ 31.60",
      "David Johnson \/ 32.70",
      "Terry McLaurin \/ 55.00",
      "Dak Prescott \/ 75.90",
      "Aaron Rodgers \/ 88.10",
      "Marvin Jones \/ 99.60",
      "Ronald Jones \/ 110.00",
      "Bears \/ 116.00",
      "Matt Breida \/ 94.00",
      "Austin Hooper \/ 132.00",
      "Jonnu Smith \/ 144.00",
      "Matt Prater \/ 165.00",
      "Kirk Cousins \/ 147.00"
    ],
    "Points Reg Season":1624.48,
    "Points Full Season":1887.74
  },
  {
    "Simulation":42,
    "Winner":"Team 3",
    "Roster":[
      "Alvin Kamara \/ 4.22",
      "Aaron Jones \/ 20.90",
      "Kenny Golladay \/ 36.40",
      "Allen Robinson \/ 47.10",
      "Russell Wilson \/ 64.80",
      "Rob Gronkowski \/ 80.50",
      "Mark Andrews \/ 71.60",
      "Delanie Walker \/ 98.70",
      "Emmanuel Sanders \/ 105.00",
      "Royce Freeman \/ 108.00",
      "Justin Tucker \/ 123.00",
      "Jerry Jeudy \/ 120.00",
      "Matthew Stafford \/ 126.00",
      "Chargers \/ 153.00",
      "Philip Rivers \/ 139.00"
    ],
    "Points Reg Season":1462.8,
    "Points Full Season":1721.54
  },
  {
    "Simulation":43,
    "Winner":"Team 9",
    "Roster":[
      "Nick Chubb \/ 13.00",
      "Tyreek Hill \/ 14.20",
      "Kenny Golladay \/ 36.40",
      "Melvin Gordon \/ 38.30",
      "T.Y. Hilton \/ 62.00",
      "DK Metcalf \/ 76.30",
      "Drew Brees \/ 80.10",
      "Michael Gallup \/ 89.80",
      "Geronimo Allison \/ 111.00",
      "Noah Fant \/ 119.00",
      "Tarik Cohen \/ 93.80",
      "Trey Burton \/ 130.00",
      "Younghoe Koo \/ 160.00",
      "Bills \/ 135.00",
      "Jimmy Garoppolo \/ 148.00"
    ],
    "Points Reg Season":1275.3,
    "Points Full Season":1469.5
  },
  {
    "Simulation":44,
    "Winner":"Team 2",
    "Roster":[
      "Ezekiel Elliott \/ 3.44",
      "Mike Evans \/ 27.90",
      "Todd Gurley \/ 24.50",
      "David Montgomery \/ 54.80",
      "Darren Waller \/ 61.30",
      "Rob Gronkowski \/ 80.50",
      "Antonio Gibson \/ 82.10",
      "Matt Breida \/ 94.00",
      "Emmanuel Sanders \/ 105.00",
      "James White \/ 83.20",
      "Aaron Rodgers \/ 88.10",
      "Deebo Samuel \/ 120.00",
      "Greg Zuerlein \/ 136.00",
      "Broncos \/ 162.00",
      "Matthew Stafford \/ 126.00"
    ],
    "Points Reg Season":1468.22,
    "Points Full Season":1742.48
  },
  {
    "Simulation":45,
    "Winner":"Team 8",
    "Roster":[
      "Alvin Kamara \/ 4.22",
      "Aaron Jones \/ 20.90",
      "Kenny Golladay \/ 36.40",
      "Calvin Ridley \/ 53.10",
      "Stefon Diggs \/ 59.00",
      "Dak Prescott \/ 75.90",
      "Sony Michel \/ 80.90",
      "Vance McDonald \/ 77.80",
      "Diontae Johnson \/ 108.00",
      "Eric Ebron \/ 119.00",
      "Darrell Henderson \/ 124.00",
      "Jerry Jeudy \/ 120.00",
      "Zane Gonzalez \/ 150.00",
      "Saints \/ 139.00",
      "Gardner Minshew \/ 155.00"
    ],
    "Points Reg Season":1514.98,
    "Points Full Season":1817.12
  },
  {
    "Simulation":46,
    "Winner":"Team 9",
    "Roster":[
      "Nick Chubb \/ 13.00",
      "Josh Jacobs \/ 19.70",
      "Melvin Gordon \/ 38.30",
      "Allen Robinson \/ 47.10",
      "Matt Ryan \/ 74.50",
      "Robert Woods \/ 53.60",
      "Carson Wentz \/ 89.30",
      "Rashaad Penny \/ 91.90",
      "Sterling Shepard \/ 113.00",
      "Drew Brees \/ 80.10",
      "Delanie Walker \/ 98.70",
      "Austin Hooper \/ 132.00",
      "Zane Gonzalez \/ 150.00",
      "Saints \/ 139.00",
      "Drew Lock \/ 155.00"
    ],
    "Points Reg Season":1214.16,
    "Points Full Season":1437.22
  },
  {
    "Simulation":47,
    "Winner":"Team 4",
    "Roster":[
      "Dalvin Cook \/ 7.95",
      "Chris Carson \/ 26.40",
      "David Johnson \/ 32.70",
      "Calvin Ridley \/ 53.10",
      "Allen Robinson \/ 47.10",
      "Dak Prescott \/ 75.90",
      "Brandin Cooks \/ 82.50",
      "Latavius Murray \/ 94.90",
      "Josh Allen \/ 105.00",
      "David Njoku \/ 83.80",
      "Deebo Samuel \/ 120.00",
      "Austin Hooper \/ 132.00",
      "Greg Zuerlein \/ 136.00",
      "Chiefs \/ 147.00",
      "Mitchell Trubisky \/ 138.00"
    ],
    "Points Reg Season":1463.74,
    "Points Full Season":1762.7
  },
  {
    "Simulation":48,
    "Winner":"Team 8",
    "Roster":[
      "Nick Chubb \/ 13.00",
      "Derrick Henry \/ 16.10",
      "Jonathan Taylor \/ 38.40",
      "Tyler Lockett \/ 52.60",
      "Stefon Diggs \/ 59.00",
      "Vance McDonald \/ 77.80",
      "Jarvis Landry \/ 82.40",
      "Will Fuller \/ 83.20",
      "Latavius Murray \/ 94.90",
      "Jared Goff \/ 114.00",
      "Darrell Henderson \/ 124.00",
      "Trey Burton \/ 130.00",
      "Mike Badgley \/ 149.00",
      "Saints \/ 139.00",
      "Kirk Cousins \/ 147.00"
    ],
    "Points Reg Season":1419.98,
    "Points Full Season":1651.3
  },
  {
    "Simulation":49,
    "Winner":"Team 3",
    "Roster":[
      "Ezekiel Elliott \/ 3.44",
      "Miles Sanders \/ 27.50",
      "Kenny Golladay \/ 36.40",
      "Terry McLaurin \/ 55.00",
      "Stefon Diggs \/ 59.00",
      "Marlon Mack \/ 79.40",
      "DK Metcalf \/ 76.30",
      "D'Andre Swift \/ 68.80",
      "A.J. Green \/ 77.60",
      "Noah Fant \/ 119.00",
      "Tom Brady \/ 94.20",
      "T.J. Hockenson \/ 138.00",
      "Justin Tucker \/ 123.00",
      "Broncos \/ 162.00",
      "Daniel Jones \/ 129.00"
    ],
    "Points Reg Season":1425.8,
    "Points Full Season":1671.32
  },
  {
    "Simulation":50,
    "Winner":"Team 5",
    "Roster":[
      "Alvin Kamara \/ 4.22",
      "Chris Carson \/ 26.40",
      "LeVeon Bell \/ 29.30",
      "Robert Woods \/ 53.60",
      "Kyler Murray \/ 71.20",
      "Marlon Mack \/ 79.40",
      "Will Fuller \/ 83.20",
      "Matt Breida \/ 94.00",
      "Marvin Jones \/ 99.60",
      "Deebo Samuel \/ 120.00",
      "Noah Fant \/ 119.00",
      "T.J. Hockenson \/ 138.00",
      "Wil Lutz \/ 137.00",
      "Rams \/ 140.00",
      "Joe Burrow \/ 143.00"
    ],
    "Points Reg Season":1546.1,
    "Points Full Season":1793.02
  }
]